astar_qa/__init__.py
astar_qa/base.py
astar_qa/dataset/__init__.py
astar_qa/dataset/data.py
astar_qa/deal/__init__.py
astar_qa/deal/deal.py
astar_qa/deal/macd_deal.py
astar_qa/strategy/__init__.py
astar_qa/strategy/macd_strategy.py
astar_qa-0.0.4a6.dist-info/METADATA
astar_qa-0.0.4a6.dist-info/RECORD
astar_qa-0.0.4a6.dist-info/WHEEL
astar_qa-0.0.4a6.dist-info/top_level.txt
